ollama_serve/__init__.py
ollama_serve/main.py
ollama_serve-0.0.1.dist-info/licenses/LICENSE
ollama_serve-0.0.1.dist-info/METADATA
ollama_serve-0.0.1.dist-info/WHEEL
ollama_serve-0.0.1.dist-info/top_level.txt
ollama_serve-0.0.1.dist-info/RECORD
