Metadata-Version: 2.4
Name: ollama-serve
Version: 0.0.1
Summary: A Python package that ensures the Ollama server is running and ready with the models your project expects.
Author: Dave Bunten
Classifier: Programming Language :: Python :: 3 :: Only
Classifier: Programming Language :: Python :: 3.11
Classifier: Programming Language :: Python :: 3.12
Classifier: Programming Language :: Python :: 3.13
Classifier: Programming Language :: Python :: 3.14
Requires-Python: >=3.11
License-File: LICENSE
Dynamic: license-file
